astromulti/__init__.py
astromulti/fits_actions.py
astromulti/linear_fitting.py
astromulti/new_colormap.py
astromulti/region_meta.py
astromulti/simple_funcs.py
astromulti-1.0.6.dist-info/LICENSE
astromulti-1.0.6.dist-info/METADATA
astromulti-1.0.6.dist-info/WHEEL
astromulti-1.0.6.dist-info/top_level.txt
astromulti-1.0.6.dist-info/RECORD
