Metadata-Version: 2.1
Name: astromulti
Version: 1.0.6
Summary: A set of functions for analysis of astronomical images
Author-email: Rohit D <rohitd@proton.me>
Project-URL: Homepage, https://gitlab.com/drohi/astromulti
Classifier: Programming Language :: Python :: 3
Classifier: License :: OSI Approved :: MIT License
Classifier: Operating System :: OS Independent
Requires-Python: >=3.7
License-File: LICENSE
